Workbook

Sheet 品类汇总
A1: 摩托车公开信息汇总 · 按品类统计（共 114 款 · 8 大品类 · 数据截至 2026-09）
A2: 品类 | B2: 车型数量 | C2: 最低价(元) | D2: 最高价(元) | E2: 均价(元) | F2: 平均排量(cc) | G2: 平均马力(Ps) | H2: 平均座高(mm)
A3: 仿赛 | B3: =COUNTIF('车型总表'!$E$2:$E$115,$A3) | C3: =MINIFS('车型总表'!$G$2:$G$115,'车型总表'!$E$2:$E$115,$A3) | D3: =MAXIFS('车型总表'!$G$2:$G$115,'车型总表'!$E$2:$E$115,$A3) | E3: =ROUND(AVERAGEIF('车型总表'!$E$2:$E$115,$A3,'车型总表'!$G$2:$G$115),0) | F3: =ROUND(AVERAGEIF('车型总表'!$E$2:$E$115,$A3,'车型总表'!$H$2:$H$115),0) | G3: =ROUND(AVERAGEIF('车型总表'!$E$2:$E$115,$A3,'车型总表'!$K$2:$K$115),1) | H3: =ROUND(AVERAGEIF('车型总表'!$E$2:$E$115,$A3,'车型总表'!$N$2:$N$115),0)
A4: 街车 | B4: =COUNTIF('车型总表'!$E$2:$E$115,$A4) | C4: =MINIFS('车型总表'!$G$2:$G$115,'车型总表'!$E$2:$E$115,$A4) | D4: =MAXIFS('车型总表'!$G$2:$G$115,'车型总表'!$E$2:$E$115,$A4) | E4: =ROUND(AVERAGEIF('车型总表'!$E$2:$E$115,$A4,'车型总表'!$G$2:$G$115),0) | F4: =ROUND(AVERAGEIF('车型总表'!$E$2:$E$115,$A4,'车型总表'!$H$2:$H$115),0) | G4: =ROUND(AVERAGEIF('车型总表'!$E$2:$E$115,$A4,'车型总表'!$K$2:$K$115),1) | H4: =ROUND(AVERAGEIF('车型总表'!$E$2:$E$115,$A4,'车型总表'!$N$2:$N$115),0)
A5: 巡航 | B5: =COUNTIF('车型总表'!$E$2:$E$115,$A5) | C5: =MINIFS('车型总表'!$G$2:$G$115,'车型总表'!$E$2:$E$115,$A5) | D5: =MAXIFS('车型总表'!$G$2:$G$115,'车型总表'!$E$2:$E$115,$A5) | E5: =ROUND(AVERAGEIF('车型总表'!$E$2:$E$115,$A5,'车型总表'!$G$2:$G$115),0) | F5: =ROUND(AVERAGEIF('车型总表'!$E$2:$E$115,$A5,'车型总表'!$H$2:$H$115),0) | G5: =ROUND(AVERAGEIF('车型总表'!$E$2:$E$115,$A5,'车型总表'!$K$2:$K$115),1) | H5: =ROUND(AVERAGEIF('车型总表'!$E$2:$E$115,$A5,'车型总表'!$N$2:$N$115),0)
A6: 复古 | B6: =COUNTIF('车型总表'!$E$2:$E$115,$A6) | C6: =MINIFS('车型总表'!$G$2:$G$115,'车型总表'!$E$2:$E$115,$A6) | D6: =MAXIFS('车型总表'!$G$2:$G$115,'车型总表'!$E$2:$E$115,$A6) | E6: =ROUND(AVERAGEIF('车型总表'!$E$2:$E$115,$A6,'车型总表'!$G$2:$G$115),0) | F6: =ROUND(AVERAGEIF('车型总表'!$E$2:$E$115,$A6,'车型总表'!$H$2:$H$115),0) | G6: =ROUND(AVERAGEIF('车型总表'!$E$2:$E$115,$A6,'车型总表'!$K$2:$K$115),1) | H6: =ROUND(AVERAGEIF('车型总表'!$E$2:$E$115,$A6,'车型总表'!$N$2:$N$115),0)
A7: 拉力ADV | B7: =COUNTIF('车型总表'!$E$2:$E$115,$A7) | C7: =MINIFS('车型总表'!$G$2:$G$115,'车型总表'!$E$2:$E$115,$A7) | D7: =MAXIFS('车型总表'!$G$2:$G$115,'车型总表'!$E$2:$E$115,$A7) | E7: =ROUND(AVERAGEIF('车型总表'!$E$2:$E$115,$A7,'车型总表'!$G$2:$G$115),0) | F7: =ROUND(AVERAGEIF('车型总表'!$E$2:$E$115,$A7,'车型总表'!$H$2:$H$115),0) | G7: =ROUND(AVERAGEIF('车型总表'!$E$2:$E$115,$A7,'车型总表'!$K$2:$K$115),1) | H7: =ROUND(AVERAGEIF('车型总表'!$E$2:$E$115,$A7,'车型总表'!$N$2:$N$115),0)
A8: 踏板 | B8: =COUNTIF('车型总表'!$E$2:$E$115,$A8) | C8: =MINIFS('车型总表'!$G$2:$G$115,'车型总表'!$E$2:$E$115,$A8) | D8: =MAXIFS('车型总表'!$G$2:$G$115,'车型总表'!$E$2:$E$115,$A8) | E8: =ROUND(AVERAGEIF('车型总表'!$E$2:$E$115,$A8,'车型总表'!$G$2:$G$115),0) | F8: =ROUND(AVERAGEIF('车型总表'!$E$2:$E$115,$A8,'车型总表'!$H$2:$H$115),0) | G8: =ROUND(AVERAGEIF('车型总表'!$E$2:$E$115,$A8,'车型总表'!$K$2:$K$115),1) | H8: =ROUND(AVERAGEIF('车型总表'!$E$2:$E$115,$A8,'车型总表'!$N$2:$N$115),0)
A9: 越野 | B9: =COUNTIF('车型总表'!$E$2:$E$115,$A9) | C9: =MINIFS('车型总表'!$G$2:$G$115,'车型总表'!$E$2:$E$115,$A9) | D9: =MAXIFS('车型总表'!$G$2:$G$115,'车型总表'!$E$2:$E$115,$A9) | E9: =ROUND(AVERAGEIF('车型总表'!$E$2:$E$115,$A9,'车型总表'!$G$2:$G$115),0) | F9: =ROUND(AVERAGEIF('车型总表'!$E$2:$E$115,$A9,'车型总表'!$H$2:$H$115),0) | G9: =ROUND(AVERAGEIF('车型总表'!$E$2:$E$115,$A9,'车型总表'!$K$2:$K$115),1) | H9: =ROUND(AVERAGEIF('车型总表'!$E$2:$E$115,$A9,'车型总表'!$N$2:$N$115),0)
A10: 电动摩托 | B10: =COUNTIF('车型总表'!$E$2:$E$115,$A10) | C10: =MINIFS('车型总表'!$G$2:$G$115,'车型总表'!$E$2:$E$115,$A10) | D10: =MAXIFS('车型总表'!$G$2:$G$115,'车型总表'!$E$2:$E$115,$A10) | E10: =ROUND(AVERAGEIF('车型总表'!$E$2:$E$115,$A10,'车型总表'!$G$2:$G$115),0) | F10: =ROUND(AVERAGEIF('车型总表'!$E$2:$E$115,$A10,'车型总表'!$H$2:$H$115),0) | G10: =ROUND(AVERAGEIF('车型总表'!$E$2:$E$115,$A10,'车型总表'!$K$2:$K$115),1) | H10: =ROUND(AVERAGEIF('车型总表'!$E$2:$E$115,$A10,'车型总表'!$N$2:$N$115),0)
A11: 全部车型 | B11: =SUM(B3:B10) | C11: =MIN('车型总表'!$G$2:$G$115) | D11: =MAX('车型总表'!$G$2:$G$115) | E11: =ROUND(AVERAGE('车型总表'!$G$2:$G$115),0) | F11: =ROUND(AVERAGE('车型总表'!$H$2:$H$115),0) | G11: =ROUND(AVERAGE('车型总表'!$K$2:$K$115),1) | H11: =ROUND(AVERAGE('车型总表'!$N$2:$N$115),0)

Sheet 车型总表
A1: 序号 | B1: 品牌 | C1: 车型 | D1: 英文名 | E1: 品类 | F1: 产地 | G1: 参考价(元) | H1: 排量(cc) | I1: 气缸型式 | J1: 最大功率(kW) | K1: 最大马力(Ps) | L1: 最大扭矩(N·m) | M1: 整备质量(kg) | N1: 座高(mm) | O1: 油箱(L) | P1: 马力/吨 | Q1: 每cc单价(元) | R1: 适用场景 | S1: 标签 | T1: 优点 | U1: 短板 | V1: 适合谁
A2: 1 | B2: 凯越 KAYO | C2: 凯越 321RR | D2: KAYO 321RR | E2: 仿赛 | F2: 国产 | G2: 23980 | H2: 322 | I2: 直列双缸 · 水冷 | J2: 30 | K2: 40.8 | L2: 24 | M2: 151 | N2: 780 | O2: 14 | P2: =IF(OR(K2="",M2="",M2=0),"",ROUND(K2/(M2/1000),0)) | Q2: =IF(OR(G2="",H2="",H2=0),"",ROUND(G2/H2,0)) | R2: 玩乐跑山 · 新手友好 | S2: 151kg超轻 · 入门仿赛 · 好上手 | T2: 151kg 车重，同级最轻之一，操控极灵活；座高 780mm，身材一般也能双脚着地；价格低，入门门槛友好 | U2: 322cc 动力上限有限，进阶后会不够用；高速稳定性一般 | V2: 第一台仿赛、预算 2.4 万以内的新手
A3: 2 | B3: 春风 CFMOTO | C3: 春风 450SR | D3: CFMOTO 450SR | E3: 仿赛 | F3: 国产 | G3: 24980 | H3: 450 | I3: 直列双缸 · 水冷 · 270°曲轴 | J3: 38 | K3: 51.7 | L3: 40 | M3: 170 | N3: 795 | O3: 14 | P3: =IF(OR(K3="",M3="",M3=0),"",ROUND(K3/(M3/1000),0)) | Q3: =IF(OR(G3="",H3="",H3=0),"",ROUND(G3/H3,0)) | R3: 通勤代步 · 玩乐跑山 · 新手友好 | S3: 销量王 · 新手友好 · 270°曲轴 · 性价比 | T3: 轻量化到位，170kg 推起来毫无压力；270° 曲轴声浪接近 V 缸，辨识度高；保有量极大，改件和保养便宜；二手保值率在国产里数一数二 | U3: 高转延展一般，万转后劲不如四缸；后座支撑偏弱，载人舒适性差 | V3: 第一次买仿赛的人、通勤与周末跑山兼顾的骑手
A4: 3 | B4: QJMOTOR 钱江 | C4: 钱江 赛550 | D4: QJMOTOR 赛550 | E4: 仿赛 | F4: 国产 | G4: 26999 | H4: 554 | I4: 直列双缸 · 水冷 | J4: 41 | K4: 55.8 | L4: 52 | M4: 190 | N4: 795 | O4: 16 | P4: =IF(OR(K4="",M4="",M4=0),"",ROUND(K4/(M4/1000),0)) | Q4: =IF(OR(G4="",H4="",H4=0),"",ROUND(G4/H4,0)) | R4: 玩乐跑山 · 通勤代步 | S4: 中排双缸 · 扭矩足 · 配置高 | T4: 554cc 双缸 52N·m，低扭充沛；标配 ABS + TCS，制动规格不低；价格在 550 级别里很有竞争力 | U4: 品牌同级车型多，容易挑花眼；车重 190kg，激进骑行偏吃力 | V4: 预算 2.7 万左右、看重扭矩与配置的仿赛用户
A5: 4 | B5: 张雪机车 | C5: 张雪 500RR | D5: Zhangxue 500RR | E5: 仿赛 | F5: 国产 | G5: 27980 | H5: 470 | I5: 直列四缸 · 水冷 | J5: 62 | K5: 84.3 | L5: 46 | M5: 172 | N5: 795 | O5: 15 | P5: =IF(OR(K5="",M5="",M5=0),"",ROUND(K5/(M5/1000),0)) | Q5: =IF(OR(G5="",H5="",H5=0),"",ROUND(G5/H5,0)) | R5: 玩乐跑山 | S5: 四缸黑马 · 84匹 · 3.4秒破百 | T5: 同价位马力最强，84.3 匹压迫感十足；弯道 ABS、快排等配置给得很足；团队愿意听玩家意见，迭代很快 | U5: 品牌新，全国服务网点偏少；长期可靠性与保值率还需时间验证 | V5: 把性能和账面数据放在第一位的玩家
A6: 5 | B6: 凯越 KAYO | C6: 凯越 450RR | D6: KAYO 450RR | E6: 仿赛 | F6: 国产 | G6: 29980 | H6: 443 | I6: 直列四缸 · 水冷 | J6: 52 | K6: 70.7 | L6: 39 | M6: 165 | N6: 795 | O6: 15 | P6: =IF(OR(K6="",M6="",M6=0),"",ROUND(K6/(M6/1000),0)) | Q6: =IF(OR(G6="",H6="",H6=0),"",ROUND(G6/H6,0)) | R6: 玩乐跑山 | S6: 国产首款四缸仿赛 · 轻量化 · 高转猛 | T6: 165kg 车重，同级最轻之一；万转之后动力爆发非常上头；四缸声浪是这个价位难得的东西 | U6: 低扭偏弱，市区代步略显费神；后减震偏硬，载人体验一般；座姿偏战斗，长途不舒服 | V6: 追求操控极限与赛道潜力的进阶玩家
A7: 6 | B7: 无极 VOGE | C7: 无极 525RR | D7: VOGE 525RR | E7: 仿赛 | F7: 国产 | G7: 29980 | H7: 494 | I7: 直列双缸 · 水冷 | J7: 40 | K7: 54.4 | L7: 44 | M7: 190 | N7: 790 | O7: 16 | P7: =IF(OR(K7="",M7="",M7=0),"",ROUND(K7/(M7/1000),0)) | Q7: =IF(OR(G7="",H7="",H7=0),"",ROUND(G7/H7,0)) | R7: 玩乐跑山 · 通勤代步 | S7: 中排四缸之外的选择 · 动力够用 · 好上手 | T7: 494cc 双缸 54 匹，动力平顺好控制；坐姿不如四缸战斗，日常通勤也能骑；配置齐全，价格落在 3 万内 | U7: 双缸声浪不如四缸有吸引力；车身偏重 190kg | V7: 想兼顾通勤与周末跑山的中排仿赛用户
A8: 7 | B8: QJMOTOR 钱江 | C8: 钱江 赛600RS | D8: QJMOTOR 赛600RS | E8: 仿赛 | F8: 国产 | G8: 34999 | H8: 680 | I8: 直列四缸 · 水冷 | J8: 74.5 | K8: 101 | L8: 68 | M8: 206 | N8: 830 | O8: 18 | P8: =IF(OR(K8="",M8="",M8=0),"",ROUND(K8/(M8/1000),0)) | Q8: =IF(OR(G8="",H8="",H8=0),"",ROUND(G8/H8,0)) | R8: 玩乐跑山 | S8: 四缸常青树 · 百匹 · Brembo | T8: 680cc 四缸 101 匹，动力储备充足；布雷博卡钳 + 马祖奇减震，硬件规格高；车型成熟，配件与改装生态完善 | U8: 206kg 车重，挪车需要技巧；油耗高，市区六七个油；座高 830mm，对矮个子不友好 | V8: 想要四缸声浪与性能、预算 3 万多的进阶玩家
A9: 8 | B9: 春风 CFMOTO | C9: 春风 675SR | D9: CFMOTO 675SR | E9: 仿赛 | F9: 国产 | G9: 39580 | H9: 674 | I9: 直列三缸 · 水冷 | J9: 70 | K9: 95.2 | L9: 70 | M9: 175 | N9: 815 | O9: 15 | P9: =IF(OR(K9="",M9="",M9=0),"",ROUND(K9/(M9/1000),0)) | Q9: =IF(OR(G9="",H9="",H9=0),"",ROUND(G9/H9,0)) | R9: 玩乐跑山 | S9: 国产三缸天花板 · 95匹 · 双向快排 | T9: 674cc 三缸 95 匹，国产中排仿赛动力标杆；KYB 全可调减震 + 西互四活塞辐射卡钳，硬件越级；标配双向快排、滑动离合、两段可调 TCS | U9: 座高 815mm 偏高，175kg 干重挪车需注意；三缸保养成本高于双缸 | V9: 预算 4 万左右、想要三缸动力与越级配置的进阶玩家
A10: 9 | B10: 雅马哈 Yamaha | C10: 雅马哈 YZF-R3 | D10: Yamaha YZF-R3 | E10: 仿赛 | F10: 进口 | G10: 46800 | H10: 321 | I10: 直列双缸 · 水冷 | J10: 30.4 | K10: 41.3 | L10: 29.6 | M10: 169 | N10: 780 | O10: 14 | P10: =IF(OR(K10="",M10="",M10=0),"",ROUND(K10/(M10/1000),0)) | Q10: =IF(OR(G10="",H10="",H10=0),"",ROUND(G10/H10,0)) | R10: 通勤代步 · 玩乐跑山 · 新手友好 | S10: 入门进口 · 轻巧 · 保值 | T10: 169kg 车轻，新手上手压力小；雅马哈品质稳定，二手保值好；座高 780mm，对多数人友好 | U10: 321cc 动力偏温和；配置基础，无快排等硬件 | V10: 想入门进口仿赛、以通勤和轻玩乐为主的新手
A11: 10 | B11: 川崎 Kawasaki | C11: 川崎 Ninja 400 | D11: Kawasaki Ninja 400 | E11: 仿赛 | F11: 进口 | G11: 49800 | H11: 399 | I11: 直列双缸 · 水冷 | J11: 35 | K11: 47.6 | L11: 38 | M11: 168 | N11: 785 | O11: 14 | P11: =IF(OR(K11="",M11="",M11=0),"",ROUND(K11/(M11/1000),0)) | Q11: =IF(OR(G11="",H11="",H11=0),"",ROUND(G11/H11,0)) | R11: 通勤代步 · 玩乐跑山 · 新手友好 | S11: 进口入门标杆 · 轻巧 · 改装潜力 | T11: 168kg 车轻，操控灵活好上手；川崎品质稳，二手保值；改装件丰富，玩车生态好 | U11: 399cc 排量偏小，进阶后会不够用；进口身份但配置一般；热门配色常有加价或等车 | V11: 想入门进口仿赛、预算 5 万左右的新手
A12: 11 | B12: 阿普利亚 Aprilia | C12: 阿普利亚 RS 457 | D12: Aprilia RS 457 | E12: 仿赛 | F12: 进口 | G12: 49800 | H12: 457 | I12: 直列双缸 · 水冷 | J12: 35 | K12: 47.6 | L12: 43.5 | M12: 175 | N12: 800 | O12: 13 | P12: =IF(OR(K12="",M12="",M12=0),"",ROUND(K12/(M12/1000),0)) | Q12: =IF(OR(G12="",H12="",H12=0),"",ROUND(G12/H12,0)) | R12: 玩乐跑山 · 通勤代步 | S12: 意式仿赛 · 175kg · 赛道基因 | T12: 175kg 车重配 47 匹，推重比出色；阿普利亚的赛道调校，弯道表现优秀；外观和做工是同级里的颜值担当 | U12: 价格偏高，配置不如国产堆料；售后网点密度不及日系 | V12: 看重操控质感与品牌调性的进阶骑手
A13: 12 | B13: KTM | C13: KTM RC 390 | D13: KTM RC 390 | E13: 仿赛 | F13: 进口 | G13: 49800 | H13: 373 | I13: 单缸 · 水冷 | J13: 32 | K13: 43.5 | L13: 36 | M13: 172 | N13: 824 | O13: 13.7 | P13: =IF(OR(K13="",M13="",M13=0),"",ROUND(K13/(M13/1000),0)) | Q13: =IF(OR(G13="",H13="",H13=0),"",ROUND(G13/H13,0)) | R13: 玩乐跑山 | S13: 单缸猛兽 · Ready to Race · WP减震 | T13: 373cc 单缸压榨出 43.5 匹，动力暴躁；WP 减震 + 轻量化车架，赛道取向明确；电控配置丰富，弯道 ABS 标配 | U13: 单缸震动明显，长途不舒适；座高 824mm，坐姿战斗 | V13: 喜欢激进风格、以赛道和山路为主的玩家
... A115: 114 | B115: 极核 ZEEHO | C115: 极核 AE8 | D115: ZEEHO AE8 | E115: 电动摩托 | F115: 国产 | G115: 17980 | H115: 0 | I115: 中置电机 · 锂电池 | J115: 12.5 | K115: 17 | L115: 218 | M115: 133 | N115: 780 | O115: 0 | P115: =IF(OR(K115="",M115="",M115=0),"",ROUND(K115/(M115/1000),0)) | Q115: =IF(OR(G115="",H115="",H115=0),"",ROUND(G115/H115,0)) | R115: 玩乐跑山 · 通勤代步 | S115: 17匹 · 极速110 · 高性能电摩 | T115: 12.5kW 中置电机，动力在电摩里第一梯队；操控与底盘调校偏运动，跑山有意思；春风旗下品牌，售后依托春风渠道 | U115: 续航约 100km，长途受限；价格接近 1.8 万 | V115: 想要电动高性能与运动操控、预算充足的城市玩家

Sheet 资料说明
A1: 一、字段定义与单位
A2: 字段 | B2: 类型 | C2: 说明
A3: 序号 | B3: 序号 | C3: 按品类分组后的行号，仅用于阅读定位
A4: 品牌 / 车型 | B4: 文本 | C4: 厂商品牌与中文车型名
A5: 英文名 | B5: 文本 | C5: 厂商官方英文或国际通称
A6: 品类 | B6: 枚举 | C6: 仿赛 / 街车 / 巡航 / 复古 / 拉力ADV / 踏板 / 越野 / 电动摩托，共 8 类
A7: 产地 | B7: 枚举 | C7: 国产 / 合资 / 进口
A8: 参考价(元) | B8: 数字 | C8: 厂商指导价或市场参考价（元）。会随促销、地区、库存明显波动
A9: 排量(cc) | B9: 数字 | C9: 发动机实际排量，单位毫升。电动摩托车无排量，记为 0，以电机功率(kW)衡量动力
A10: 气缸型式 | B10: 文本 | C10: 气缸排列 + 冷却方式 + 特殊结构（如 270° 曲轴）
A11: 最大功率(kW) | B11: 数字（1位小数） | C11: 发动机最大功率，千瓦
A12: 最大马力(Ps) | B12: 数字（1位小数） | C12: 最大功率的公制马力换算值
A13: 最大扭矩(N·m) | B13: 数字（1位小数） | C13: 发动机峰值扭矩
... A21: 适合谁 | B21: 文本 | C21: 该车最匹配的典型用户画像
A23: 二、数据来源
A24: 来源类型 | B24: 用于 | C24: 说明
A25: 厂商官方渠道 | B25: 参数与价格 | C25: 春风 CFMOTO、无极 VOGE、QJMOTOR、凯越、奔达、豪爵、本田、雅马哈、川崎、宝马、杜卡迪、哈雷、凯旋等品牌官网与官方发布稿
A26: 公开汽车/摩托媒体 | B26: 参数、价格、评测 | C26: 汽车之家、易车、摩托范（58moto）、今日头条车家号、百度百科等公开报道与实测文章
A27: 电商官方旗舰店 | B27: 在售价格校准 | C27: 京东/天猫摩托车自营专区等公开挂牌价，用于校准厂商指导价与实际成交区间
A28: 公开图库 | B28: 车型照片 | C28: 品牌官网、上述媒体公开图库；图片仅用于个人选购参考，版权归原作者所有
A29: 整理时间 | B29: — | C29: 2026 年 9 月
A31: 三、使用与免责说明
A32: 事项 | B32: — | C32: 说明
A33: 价格波动 | B33: — | C33: 本表价格为厂商指导价或市场参考价。实际成交价受地区、经销商促销、库存、选装配置影响，可能有数千至数万元的差异，购车前请以经销商店内实车报价为准。
A34: 参数口径 | B34: — | C34: 技术参数以厂商官方公布为准。同一车型不同年份改款、不同配置版本（如标准版/三箱版/Pro 版）参数会有差异，本表取主流在售版本的代表值。
A35: 换算说明 | B35: — | C35: 马力为公制马力（Ps），1 kW ≈ 1.36 Ps；马力/吨与每cc单价为本表派生的参考指标，用于横向对比，非厂商官方口径。
A36: 选购提示 | B36: — | C36: 参数决定性能上限，用车场景决定满意度。建议先定预算与用途，再按座高筛选，最后到店试驾确认。新手不建议直接上 500cc 以上或高马力车型。
A37: 版权声明 | B37: — | C37: 本表由公开信息整理汇编，仅供个人学习与选购参考，不构成任何购买建议或商业承诺。
